Metadata-Version: 2.1
Name: scrape-google-scholar
Version: 1.0.2
Summary: A python library to scrape google scholar search
Home-page: UNKNOWN
Author: DataKund
Author-email: datakund@gmail.com
License: Apache License 2.0
Keywords: google python bot_studio automation search scholar result scraper title description link
Platform: UNKNOWN
License-File: LICENSE
